[
  { "subcategory": "체크카드", "title": "체크카드 신청할 때 '부재 시 대리수령'에 동의했어요. 수령인 기준은 어떻게 되나요?", 
    "content": "<p>체크카드 신청 시 선택한 배송지에 따라 대리수령인 기준이 상이합니다.</p><p>· 자택 : 가족(미성년자 제외)이 대리수령<p>· 직장 : 직장동료가 대리수령</p><p>· 기타 : 가족(미성년자 제외) 또는 직장동료가 대리수령</p><br><p>※ 배송기사님께서 정확한 배송을 위해 카드신청인과 대리수령인의 관계를 확인하며, 미성년자 및 일반 지인에게는 배송이 거부될 수 있으니 유의해주시기 바랍니다.</p>" },
  { "subcategory": "체크카드", "title": "카드 사용등록 방법은 어떻게 되나요?", 
    "content": "<p>본인이 직접 카드를 수령하신 경우, 수령 후 1시간 내에 자동으로 사용등록 됩니다. 만약 카드를 대리수령했거나 수령 즉시 카드 사용을 원하신다면, 카카오뱅크 모바일앱 혹은 ARS(1599-8400)를 통해 사용등록 하실 수 있습니다.</p><br><p>[카카오뱅크 모바일앱 경로 안내]</p><p>· <span class=\"navy_line\">내 카드 바로가기</span></p><p>· 홈 화면 우측 하단 전체탭( ··· ) > 내 카드 > 사용등록</p>" },
  { "subcategory": "체크카드", "title": "카드 이용내역을 엑셀 파일로 받아보고 싶어요.", 
    "content": "<p>카카오뱅크 모바일앱에서 엑셀파일의 카드 이용내역을 이메일로 받아볼 수 있습니다.</p><br><p>[카카오뱅크 모바일앱 경로 안내]</p><p>· <span class=\"navy_line\">내 카드 바로가기</span></p><p>· 홈 화면 오른쪽 하단 전체탭( ··· ) > 내 카드 > 카드관리 > 카드 이용내역 다운로드</p><br><p>※ 유의해주세요</p><p>· 제출 용도로 거래내역 파일이 필요하신 경우에는 [카카오뱅크 모바일앱 > 홈 화면 오른쪽 하단 전체탭( ··· )  > 고객센터 > 증명서 발급 > 카드] 메뉴를 이용해주세요.</p>" },
  { "subcategory": "체크카드", "title": "해외원화결제(DCC) 차단이란?", 
    "content": "<p>해외원화결제차단이란, 해외가맹점 결제 시 원화로 결제되는 것을 차단하는 기능입니다.</p><p>해외 카드 결제 구조상 온/오프라인 해외가맹점에서 원화로 결제할 경우 환전수수료가 추가 발생할 수 있으며, 이를 원하지 않는다면 해외원화결제를 카카오뱅크 모바일앱에서 차단할 수 있습니다.</p><br><p>※ 해외원화결제 차단 시, 기본 결제 통화가 원화로 설정된 해외가맹점/ATM에서는 거래 승인/출금이 거절될 수 있습니다. 해외 결제 시 가맹점의 결제 통화를 확인해주세요.</p><br><p>[카카오뱅크 모바일앱 경로 안내]</p><p>· <span class=\"navy_line\">내 카드 바로가기</span></p>· 홈 화면 오른쪽 하단 전체탭( ··· ) > 내 카드 > 카드관리 > 해외 원화(￦) 결제 차단</p>" },
  { "subcategory": "체크카드", "title": "체크카드를 자동이체 카드로 등록할 수 있나요?", 
    "content": "<p>네, 체크카드도 자동이체 카드로 등록할 수 있습니다.</p><p>단, 자동이체 처리일자에 체크카드와 연결된 계좌에 출금가능 잔액이 있어야 정상 승인처리됩니다.</p>" },
  { "subcategory": "체크카드", "title": "후불교통카드 사용 시 청구는 어떻게 하나요?", 
    "content": "<p>매월 1일부터 말일까지 사용한 후불교통 이용대금은 익월 10일 카드와 연결된 계좌에서 출금됩니다.</p><p>납부할 후불교통 이용대금이 있거나, 연체된 후불교통 이용대금이 있다면 아래 경로에서 대금을 납부하실 수 있습니다.</p><br><p>[카카오뱅크 모바일앱 경로 안내]</p><p>· <span class=\"navy_line\">내 카드 바로가기</span></p><p>· 경로 : [카카오뱅크 모바일앱 > 전체탭( ··· ) > 내 카드 > 최상단 메시지 클릭 > 교통 이용대금 납부]</p><br><p>[납부 가능 방법]</p><p>· 즉시출금</p><p>· 가상계좌 납부</p><p>※ 즉시출금은 후불교통 이용대금 발생한 카드에 연결된 계좌가 1종인 경우, 평일에 이용하실 수 있습니다.</p>" },
  { "subcategory": "체크카드", "title": "교통이용 내역을 어디서 확인할 수 있나요?", 
    "content": "<p>카카오뱅크 모바일앱에서 교통 이용내역을 확인할 수 있습니다.</p><br><p>[카카오뱅크 모바일앱 경로 안내]</p><p>· <span class=\"navy_line\">내 카드 바로가기</span></p><p>· 홈 화면 오른쪽 하단 전체탭( ··· ) > 내 카드 > 카드관리 > 교통 이용내역 조회</p>" },
  { "subcategory": "체크카드", "title": "카드 분실 신고를 했습니다. 재발급 받으려면 어떻게 해야 하나요?", 
    "content": "<p>카드 분실신고를 하셨다면 재발급 신청이 가능합니다.</p><p>신청 방법별 가능한 조건을 확인하시고, 재발급 해주세요.</p><br><p>■ 재발급 신청 방법 </p><p>· 카카오뱅크 모바일앱을 통해 신청할 경우 : 국내외 겸용여부, 후불교통기능 여부 등 카드 조건을 선택 가능</p><p>· 고객센터를 통해 신청할 경우 : 기존 카드와 동일한 조건으로만 신청 가능</p><br><p>[카카오뱅크 모바일앱 경로 안내]</p><p>· <span class=\"navy_line\">내 카드 바로가기</span></p><p>· 홈 화면 오른쪽 하단 전체탭( ··· ) > 내 카드 > 카드관리 > 카드 재발급 신청</p>" },
  { "subcategory": "체크카드", "title": "카드를 일시적으로 정지할수 있나요?", 
    "content": "<p>네, 카카오뱅크 모바일앱에서 카드를 일시정지할 수 있습니다.</p><p>단, 국내/해외 거래를 정지해도 '철도승차권 취소수수료', 후불교통요금 등 승인없이 카드사로 결제정보가 전달되는 거래는 출금 처리될 수 있습니다.</p><br><p>[카카오뱅크 모바일앱 경로 안내]</p><p>· <span class=\"navy_line\">내 카드 바로가기</span></p><p>· 홈 화면 오른쪽 하단 전체탭( ··· ) > 내 카드 > 카드관리 > 카드사용</p>" },
  { "subcategory": "체크카드", "title": "카드 결제내역을 알림으로 받고 싶은데 어떻게 신청하나요?", 
    "content": "<p>체크카드 결제알림은 앱푸시, 알림톡, SMS 중 원하는 방법으로 받을 수 있으며, 카카오뱅크 모바일앱에서 설정 가능합니다.</p><p>또한 하단의 '잔액을 표시하겠습니다' 옵션을 선택하면, 알림에서 결제 후 계좌의 잔액도 함께 확인할 수 있습니다.</p><br><p>[카카오뱅크 모바일앱 경로 안내]</p><p>· <span class=\"navy_line\">입출금/카드결제 알림 바로가기</span></p><p>· 홈 화면 오른쪽 하단 전체탭( ··· ) > 오른쪽 상단 설정 > 입출금/카드결제 알림</p>" },
  { "subcategory": "K-패스", "title": "K-패스 혜택은 어떻게 받을 수 있나요?", "content": "카드 답변 내용 011입니다." },
  { "subcategory": "K-패스", "title": "'K-패스' 적립금 혜택과 '프렌즈 캐시백 프로모션'은 무슨 차이인가요?", "content": "카드 답변 내용 012입니다." },
  { "subcategory": "K-패스", "title": "제가 가지고 있는 프렌즈 체크카드로 K-패스를 이용할 수 있나요?", "content": "카드 답변 내용 013입니다." },
  { "subcategory": "K-패스", "title": "K-패스 적립 내역을 확인하고 싶어요", "content": "카드 답변 내용 014입니다." },
  { "subcategory": "K-패스", "title": "K-패스 적립금 지급기준은 무엇인가요?", "content": "카드 답변 내용 015입니다." },
  { "subcategory": "K-패스", "title": "K-패스 적립금 지급일은 언제인가요?", "content": "카드 답변 내용 016입니다." },
  { "subcategory": "앱카드", "title": "앱카드로 결제하는 방법을 알고 싶어요.", "content": "카드 답변 내용 017입니다." },
  { "subcategory": "앱카드", "title": "PC에서도 앱카드로 결제할 수 있나요?", "content": "카드 답변 내용 018입니다." },
  { "subcategory": "앱카드", "title": "앱카드 서비스에 카드 등록 시 에러가 납니다.", "content": "카드 답변 내용 019입니다." },
  { "subcategory": "앱카드", "title": "앱카드 결제 금액에 제한이 있나요?", "content": "카드 답변 내용 020입니다." },
  { "subcategory": "앱카드", "title": "앱카드 결제가 가능한 가맹점은 어디인가요?", "content": "카드 답변 내용 021입니다." },
  { "subcategory": "앱카드", "title": "카드 신청 시, 앱카드 신청을 하지 못한 경우에는 앱카드를 사용할 수 없나요?", "content": "카드 답변 내용 022입니다." },
  { "subcategory": "앱카드", "title": "카드 신청 후 실물카드를 받기전에 앱카드를 사용할 수 있나요?", "content": "카드 답변 내용 023입니다." },
  { "subcategory": "앱카드", "title": "스마트폰 변경(기기/번호이동)을 한 경우에도 앱카드를 사용할 수 있나요?", "content": "카드 답변 내용 024입니다." },
  { "subcategory": "앱카드", "title": "앱카드를 이용할 수 있는 조건이 무엇인가요?", "content": "카드 답변 내용 025입니다." },
  { "subcategory": "체크카드", "title": "연체된 후불교통 이용대금을 납부하고 싶어요.", "content": "카드 답변 내용 026입니다." },
  { "subcategory": "체크카드", "title": "후불교통 이용대금이 자동출금되기 전에 미리 납부하고 싶어요.", "content": "카드 답변 내용 027입니다." },
  { "subcategory": "혜택 좋은 신용카드", "title": "누구나 신용카드를 신청할 수 있나요?", "content": "카드 답변 내용 028입니다." },
  { "subcategory": "혜택 좋은 신용카드", "title": "현금 이벤트 받는 카드만 조회하기가 무엇인가요?", "content": "카드 답변 내용 029입니다." },
  { "subcategory": "혜택 좋은 신용카드", "title": "현금 이벤트는 어떻게 참여하나요?", "content": "카드 답변 내용 030입니다." },
  { "subcategory": "혜택 좋은 신용카드", "title": "신청했던 카드의 이벤트를 다시 보고싶어요", "content": "카드 답변 내용 031입니다." },
  { "subcategory": "혜택 좋은 신용카드", "title": "어떤 서비스인가요?", "content": "카드 답변 내용 032입니다." },
  { "subcategory": "개인사업자 제휴 현대카드", "title": "현대카드의 세금신고용 카드이용내역은 어떻게 발급 받을 수 있나요?", "content": "카드 답변 내용 033입니다." },
  { "subcategory": "개인사업자 제휴 현대카드", "title": "BUSINESS 현대카드를 해지하고, 다시 발급해도 우대금리 혜택 받을 수 있나요?", "content": "카드 답변 내용 034입니다." },
  { "subcategory": "개인사업자 제휴 현대카드", "title": "적용 가능한 우대금리는 어디서 확인할 수 있나요?", "content": "카드 답변 내용 035입니다." },
  { "subcategory": "개인사업자 제휴 현대카드", "title": "BUSINESS 현대카드 발급 받고 카카오뱅크 사업자 신용대출 신청했는데요. 우대금리는 언제부터 적용되나요?", "content": "카드 답변 내용 036입니다." },
  { "subcategory": "개인사업자 제휴 현대카드", "title": "신용카드 신청을 취소하고 싶은데 어떻게 해아 하나요?", "content": "카드 답변 내용 037입니다." },
  { "subcategory": "개인사업자 제휴 현대카드", "title": "포인트 적립률 5% 대상 가맹점에서 사용했는데 적립되지 않았습니다.", "content": "카드 답변 내용 038입니다." },
  { "subcategory": "개인사업자 제휴 현대카드", "title": "신용카드 결제일과 결제 계좌를 변경하고 싶어요.", "content": "카드 답변 내용 039입니다." },
  { "subcategory": "개인사업자 제휴 현대카드", "title": "카카오뱅크 BUSINESS 현대카드는 누구나 신청할 수 있나요?", "content": "카드 답변 내용 040입니다." },
  { "subcategory": "모임 체크카드", "title": "모임 체크카드는 누구나 발급할 수 있나요?", "content": "카드 답변 내용 041입니다." },
  { "subcategory": "모임 체크카드", "title": "모임통장에서는 반드시 모임 체크카드만 발급해야 하나요?", "content": "카드 답변 내용 042입니다." },
  { "subcategory": "모임 체크카드", "title": "기존에 프렌즈 체크카드를 쓰고 있는 개인통장을 모임 통장으로 전환하였습니다. 프렌즈 체크카드를 계속 쓸 수 있나요?", "content": "카드 답변 내용 043입니다." },
  { "subcategory": "체크카드", "title": "카드 전월실적은 어떻게 확인하나요?", "content": "카드 답변 내용 044입니다." },
  { "subcategory": "모임 체크카드", "title": "모임 체크카드는 모임통장을 유지하는 경우에만 사용할 수 있나요?", "content": "카드 답변 내용 045입니다." },
  { "subcategory": "국세청 사업용 계좌/카드 등록", "title": "국세청 사업용 계좌/카드 등록 제도는 무엇인가요?", "content": "카드 답변 내용 046입니다." },
  { "subcategory": "국세청 사업용 계좌/카드 등록", "title": "왜 국세청에 사업용 계좌/카드를 등록해야하나요?", "content": "카드 답변 내용 047입니다." },
  { "subcategory": "국세청 사업용 계좌/카드", "title": "모든 사업자가 반드시 국세청에 사업용 계좌/카드를 등록해야하나요?", "content": "카드 답변 내용 048입니다." },
  { "subcategory": "국세청 사업용 계좌/카드", "title": "의무신고 대상자는 국세청에 사업용 계좌/카드를 언제까지 등록해야 하나요?", "content": "카드 답변 내용 049입니다." },
  { "subcategory": "국세청 사업용 계좌/카드", "title": "'국세청 사업용 계좌/카드' 서비스를 이용하려면 무엇이 필요하나요?", "content": "카드 답변 내용 050입니다." },
  { "subcategory": "국세청 사업용 계좌/카드", "title": "사업용 계좌/카드 등록 조건이 어떻게 되나요?", "content": "카드 답변 내용 051입니다." },
  { "subcategory": "국세청 사업용 계좌/카드", "title": "사업용 계좌/카드를 등록 후, 결과를 바로 확인할 수 있나요?", "content": "카드 답변 내용 052입니다." },
  { "subcategory": "국세청 사업용 계좌/카드", "title": "세무서나 홈택스에서 등록한 계좌/카드도 조회되나요?", "content": "카드 답변 내용 053입니다." },
  { "subcategory": "국세청 사업용 계좌/카드", "title": "국세청에 등록한 계좌/카드는 사업용도로만 써야하나요?", "content": "카드 답변 내용 054입니다." },
  { "subcategory": "국세청 사업용 계좌/카드", "title": "카드 목록에서 '접수완료', '확인중', '불일치'는 어떤 상태인가요?", "content": "카드 답변 내용 055입니다." },
  { "subcategory": "mini카드", "title": "카드를 사용하려는데 잔액이 부족하다고 해요.", "content": "카드 답변 내용 056입니다." },
  { "subcategory": "mini카드", "title": "mini에 잔액이 있는데 티머니(교통카드) 사용이 안돼요.", "content": "카드 답변 내용 057입니다." },
  { "subcategory": "카드 청구금액 알림", "title": "오픈뱅킹 서비스를 해지하고 싶어요.", "content": "카드 답변 내용 058입니다." },
  { "subcategory": "카드 청구금액 알림", "title": "카드사 연결을 해지하고 싶어요.", "content": "카드 답변 내용 059입니다." },
  { "subcategory": "카드 청구금액 알림", "title": "청구서 알림이 오지 않아요.", "content": "카드 답변 내용 060입니다." },
  { "subcategory": "카드 청구금액 알림", "title": "청구서 내역이 실제와 다릅니다.", "content": "카드 답변 내용 061입니다." },
  { "subcategory": "카드 청구금액 알림", "title": "카카오뱅크 체크카드가 조회되지 않습니다.", "content": "카드 답변 내용 062입니다." },
  { "subcategory": "카드 청구금액 알림", "title": "보유중인 카드가 조회되지 않습니다.", "content": "카드 답변 내용 063입니다." },
  { "subcategory": "카드 청구금액 알림", "title": "오픈뱅킹에 등록되었다는 문자를 받았습니다.", "content": "카드 답변 내용 064입니다." },
  { "subcategory": "카드 청구금액 알림", "title": "서비스 이용이 불가능한 시간이 있나요?", "content": "카드 답변 내용 065입니다." },
  { "subcategory": "카드 청구금액 알림", "title": "누구나 이용할 수 있는 서비스인가요?", "content": "카드 답변 내용 066입니다." },
  { "subcategory": "카드 청구금액 알림", "title": "어떤 서비스인가요?", "content": "카드 답변 내용 067입니다." },
  { "subcategory": "mini카드", "title": "mini카드로 티머니 충전은 어떻게 하나요?", "content": "카드 답변 내용 068입니다." },
  { "subcategory": "mini카드", "title": "카카오뱅크앱에서 충전한 티머니 잔액은 어떻게 환불하나요?", "content": "카드 답변 내용 069입니다." },
  { "subcategory": "국내주식 투자", "title": "국내주식 투자 서비스를 신청할 수 없다고 나와요.", "content": "카드 답변 내용 070입니다." },
  { "subcategory": "개인사업자 제휴 삼성카드", "title": "카카오뱅크 개인사업자 삼성카드는 누구나 신청할 수 있나요?", "content": "카드 답변 내용 071입니다." },
  { "subcategory": "개인사업자 제휴 삼성카드", "title": "신용카드 결제일과 결제 계좌를 변경하고 싶어요.", "content": "카드 답변 내용 072입니다." },
  { "subcategory": "개인사업자 제휴 삼성카드", "title": "신용카드 신청을 취소하고 싶은데 어떻게 해야 하나요?", "content": "카드 답변 내용 073입니다." },
  { "subcategory": "개인사업자 제휴 삼성카드", "title": "삼성카드의 세금신고용 이용내역 자동발송 서비스는 어떻게 ON/OFF 할 수 있나요?", "content": "카드 답변 내용 074입니다." },
  { "subcategory": "개인사업자 제휴 삼성카드", "title": "삼성카드의 세금신고용 이용내역 자동발송 받는 이메일을 변경하고 싶어요.", "content": "카드 답변 내용 075입니다." },
  { "subcategory": "개인사업자 체크카드", "title": "기존에 프렌즈 체크카드를 쓰고 있는 개인통장을 사업자통장으로 전환하였습니다. 프렌즈 체크카드를 계속 쓸 수 있나요?", "content": "카드 답변 내용 076입니다." },
  { "subcategory": "개인사업자 체크카드", "title": "해외 결제금액에 대한 캐시백은 어디서 확인할 수 있나요?", "content": "카드 답변 내용 077입니다." },
  { "subcategory": "개인사업자 체크카드", "title": "세금신고용 이용내역 자동발송이란 무엇인가요?", "content": "카드 답변 내용 078입니다." },
  { "subcategory": "개인사업자 체크카드", "title": "세금신고용 이용내역 자동발송 서비스는 ON/OFF 할 수 있나요?", "content": "카드 답변 내용 079입니다." },
  { "subcategory": "개인사업자 체크카드", "title": "사업장이 휴/폐업한 경우에도 개인사업자 체크카드를 이용할 수 있나요?", "content": "카드 답변 내용 080입니다." },
  { "subcategory": "개인사업자 체크카드", "title": "개인사업자 통장에서는 반드시 개인사업자 체크카드만 발급해야 하나요?", "content": "카드 답변 내용 081입니다." },
  { "subcategory": "개인사업자 체크카드", "title": "개인사업자 체크카드는 누구나 발급할 수 있나요?", "content": "카드 답변 내용 082입니다." },
  { "subcategory": "체크카드", "title": "체크카드 유효기한이 만료되면 어떻게 되나요? 재발급 해야 하나요?", "content": "카드 답변 내용 083입니다." },
  { "subcategory": "프렌즈 체크카드", "title": "프렌즈 체크카드 자동갱신 시 카드 디자인은 어떻게 되나요?", "content": "카드 답변 내용 084입니다." },
  { "subcategory": "체크카드", "title": "신청하지 않았는데, 체크카드가 자동으로 발급되었습니다.", "content": "카드 답변 내용 085입니다." },
  { "subcategory": "체크카드", "title": "체크카드 자동갱신 예정 문자를 받았는데, 카드가 발급되지 않았습니다.", "content": "카드 답변 내용 086입니다." },
  { "subcategory": "체크카드", "title": "후불교통카드 연체대금 입금 후 교통카드는 언제 이용 가능한가요?", "content": "카드 답변 내용 087입니다." },
  { "subcategory": "체크카드", "title": "체크카드 이용은 가능한데 교통카드 이용이 되지 않아요. 어떻게 된건가요?", "content": "카드 답변 내용 088입니다." },
  { "subcategory": "프렌즈 체크카드", "title": "카카오뱅크 카드실적 위젯이란 무엇인가요?", "content": "카드 답변 내용 089입니다." },
  { "subcategory": "체크카드", "title": "체크카드 수령 전에 결제할 수 있는 방법이 있나요?", "content": "카드 답변 내용 090입니다." },
  { "subcategory": "체크카드", "title": "체크카드를 등록할 수 있는 간편결제 서비스를 알려주세요.", "content": "카드 답변 내용 091입니다." },
  { "subcategory": "체크카드", "title": "체크카드 연결계좌를 변경할 수 있나요?", "content": "카드 답변 내용 092입니다." },
  { "subcategory": "증권사 주식계좌", "title": "주식계좌를 개설하기 위해 준비해야하는 것은 무엇인가요?", "content": "카드 답변 내용 093입니다." },
  { "subcategory": "체크카드", "title": "카드를 무선충전기와 함께 보관하면 손상될 수 있나요?", "content": "카드 답변 내용 094입니다." },
  { "subcategory": "체크카드", "title": "해외안심결제서비스를 이용 가능한 가맹점을 어떻게 확인할 수 있나요?", "content": "카드 답변 내용 095입니다." },
  { "subcategory": "체크카드", "title": "해외에서 해외안심결제서비스를 이용할 수 있나요?", "content": "카드 답변 내용 096입니다." },
  { "subcategory": "체크카드", "title": "해외안심결제서비스 어떻게 해지하나요?", "content": "카드 답변 내용 097입니다." },
  { "subcategory": "체크카드", "title": "카카오뱅크체크카드도 해외안심결제 서비스 이용이 가능한가요?", "content": "카드 답변 내용 098입니다." },
  { "subcategory": "체크카드", "title": "온라인 해외사이트에서 카드 결제가 계속 거절되는데 어떻게 해야 하나요?", "content": "카드 답변 내용 099입니다." },
  { "subcategory": "체크카드", "title": "해외ATM기를 통해 예금 통장 잔액을 인출할 수 있나요? (해외에서 체크카드로 예금인출이 가능한가요?)", "content": "카드 답변 내용 100입니다." },
  { "subcategory": "체크카드", "title": "ATM/CD 이용한도는 어떻게 되나요?", "content": "카드 답변 내용 101입니다." },
  { "subcategory": "체크카드", "title": "한 카드로 여러건의 통신요금(휴대폰 집전화 인터넷 등) 자동납부가 가능한가요?", "content": "카드 답변 내용 102입니다." },
  { "subcategory": "체크카드", "title": "통신요금(휴대폰 집전화 인터넷 등)자동납부는 어떻게 신청 또는 해지하나요?", "content": "카드 답변 내용 103입니다." },
  { "subcategory": "체크카드", "title": "해외에서 신용카드를 많이 사용하면 세무조사를 받는다던데 사실인가요?", "content": "카드 답변 내용 104입니다." },
  { "subcategory": "체크카드", "title": "해외사용 이의신청방법을 알려주세요.", "content": "카드 답변 내용 105입니다." },
  { "subcategory": "체크카드", "title": "해외에 나가지도 않았는데 승인문자를 받았어요. 어떻게 해야하나요?", "content": "카드 답변 내용 106입니다." },
  { "subcategory": "체크카드", "title": "해외에서 카드를 분실했는데 임시카드 발급이 가능한가요?", "content": "카드 답변 내용 107입니다." },
  { "subcategory": "체크카드", "title": "해외 거래 취소 시 유의사항에 대하여 알고 싶어요", "content": "카드 답변 내용 108입니다." },
  { "subcategory": "체크카드", "title": "해외에서 이용한 가맹점 정보를 확인할 수 있나요?", "content": "카드 답변 내용 109입니다." },
  { "subcategory": "체크카드", "title": "해외사용 내역에 환율이 너무 높게 적용된 것 같습니다. 어떤 환율이 적용된 것입니까", "content": "카드 답변 내용 110입니다." },
  { "subcategory": "체크카드", "title": "해외에서 물품 구매를 하였습니다. 어떻게 청구(출금)되나요?", "content": "카드 답변 내용 111입니다." },
  { "subcategory": "체크카드", "title": "해외에서 카드 거래 시 현지통화와 원화 중 어떤게 유리한가요?", "content": "카드 답변 내용 112입니다." },
  { "subcategory": "체크카드", "title": "해외에서 체크카드로 거래시 실시간으로 통장에서 출금되나요", "content": "카드 답변 내용 113입니다." },
  { "subcategory": "체크카드", "title": "카드 영문명이 여권과 다른데 해외에서 이용할 수 있나요?", "content": "카드 답변 내용 114입니다." },
  { "subcategory": "체크카드", "title": "해외에서 카카오뱅크 상담센터로 전화할 수 있나요?", "content": "카드 답변 내용 115입니다." },
  { "subcategory": "체크카드", "title": "해외브랜드별 해외에서 카드사용 제한지역이 있나요?", "content": "카드 답변 내용 116입니다." },
  { "subcategory": "체크카드", "title": "이미 사용중인 체크카드에서 후불교통기능만 비활성화할 수 있나요?", "content": "카드 답변 내용 117입니다." },
  { "subcategory": "체크카드", "title": "후불교통카드를 해지하고 싶은데 교통요금은 어떻게 처리해야 하나요?", "content": "카드 답변 내용 118입니다." },
  { "subcategory": "체크카드", "title": "교통이용 사실이 없는데 교통대금이 청구 되었어요. 어떻게 된건가요?", "content": "카드 답변 내용 119입니다." },
  { "subcategory": "체크카드", "title": "타 교통카드와 함께 지갑에 넣고 승차하면, 모두 승인이 되나요?", "content": "카드 답변 내용 120입니다." },
  { "subcategory": "체크카드", "title": "후불교통카드는 어떻게 이용하나요?", "content": "카드 답변 내용 121입니다." },
  { "subcategory": "체크카드", "title": "후불교통카드 사용지역은 어떻게 되나요?", "content": "카드 답변 내용 122입니다." },
  { "subcategory": "체크카드", "title": "후불교통카드가 발급이 안 되는 경우가 있나요?", "content": "카드 답변 내용 123입니다." },
  { "subcategory": "체크카드", "title": "최근 발생하는 카드 위/변조 사고사례는 어떤게 있나요?", "content": "카드 답변 내용 124입니다." },
  { "subcategory": "체크카드", "title": "사고보상 처리기준이 어떻게 되나요?", "content": "카드 답변 내용 125입니다." },
  { "subcategory": "체크카드", "title": "체크카드도 보상신청이 가능한가요?", "content": "카드 답변 내용 126입니다." },
  { "subcategory": "체크카드", "title": "최근 발생하는 비밀번호 유출사례는 어떤게 있나요?", "content": "카드 답변 내용 127입니다." },
  { "subcategory": "체크카드", "title": "최근 발생하는 해외 도난분실 사고사례는 어떤게 있나요?", "content": "카드 답변 내용 128입니다." },
  { "subcategory": "체크카드", "title": "분실신고를 했는데 카드를 찾았습니다. 분실신고 해제는 어떻게 하나요?", "content": "카드 답변 내용 129입니다." },
  { "subcategory": "체크카드", "title": "카드 분실신고를 본인이 아닌 다른 사람이 해도 되나요?", "content": "카드 답변 내용 130입니다." },
  { "subcategory": "체크카드", "title": "카드 이용내역서 변경방법은 어떻게 되나요?", "content": "카드 답변 내용 131입니다." },
  { "subcategory": "", "title": "이용내역서를 이메일로 못 받았는데 재발송 요청은 어떻게 하나요?", "content": "카드 답변 내용 132입니다." },
  { "subcategory": "체크카드", "title": "카드 사용한 가맹점 정보를 확인하고 싶습니다. 어떻게 하면 되나요?", "content": "카드 답변 내용 133입니다." },
  { "subcategory": "체크카드", "title": "매출취소를 했는데 언제 환불되나요?", "content": "카드 답변 내용 134입니다." },
  { "subcategory": "체크카드", "title": "매출취소를 했는데 어떻게 하나요?", "content": "카드 답변 내용 135입니다." },
  { "subcategory": "체크카드", "title": "승인취소와 매출취소의 차이점은 무엇인가요?", "content": "카드 답변 내용 136입니다." },
  { "subcategory": "체크카드", "title": "체크카드로 철도승차권을 결제 후 취소했어요, 취소수수료는 어떻게 출금되나요", "content": "카드 답변 내용 137입니다." },
  { "subcategory": "체크카드", "title": "Key-in 승인과 Full-swipe 승인의 차이점이 뭔가요?", "content": "카드 답변 내용 138입니다." },
  { "subcategory": "체크카드", "title": "카드 승인건을 취소한 적이 없는데 통장에 입금이 되었습니다. 왜 그런건가요?", "content": "카드 답변 내용 139입니다." },
  { "subcategory": "체크카드", "title": "승인내역 확인 도중 미접수 건을 발견했습니다. 어떻게 해야 하나요?", "content": "카드 답변 내용 140입니다." },
  { "subcategory": "체크카드", "title": "카드 이용한도를 하향 조정하고 싶습니다.", "content": "카드 답변 내용 141입니다." },
  { "subcategory": "체크카드", "title": "체크카드 결제계좌를 타행 계좌로 등록할 수 있나요?", "content": "카드 답변 내용 142입니다." },
  { "subcategory": "체크카드", "title": "카드에 영문 성명이 잘못 기재되어 발급되었어요, 영문 성명을 어떻게 변경하나요?", "content": "카드 답변 내용 143입니다." },
  { "subcategory": "체크카드", "title": "재발급 신청을 했는데 취소 하고 싶어요 어떻게 해야 되나요?", "content": "카드 답변 내용 144입니다." },
  { "subcategory": "체크카드", "title": "체크카드 갱신발급은 어떻게 이루어지나요?", "content": "카드 답변 내용 145입니다." },
  { "subcategory": "체크카드", "title": "카드 배송업체 연락처를 알고 싶어요", "content": "카드 답변 내용 146입니다." },
  { "subcategory": "체크카드", "title": "앱에서 카드를 신청했는데 배송방법은 어떻게 되나요?", "content": "카드 답변 내용 147입니다." },
  { "subcategory": "체크카드", "title": "체크카드를 신청했는데 취소하려면 어떻게 해야되나요?", "content": "카드 답변 내용 148입니다." },
  { "subcategory": "체크카드", "title": "카드발급이 안 된다고 하는데 왜 그런건가요?", "content": "카드 답변 내용 149입니다." },
  { "subcategory": "체크카드", "title": "외국인인데 카드발급이 가능한가요?", "content": "카드 답변 내용 150입니다." },
  { "subcategory": "체크카드", "title": "가족카드를 발급받고 싶은데 가능한가요?", "content": "카드 답변 내용 151입니다." },
  { "subcategory": "체크카드", "title": "스마트폰에서 암호화된 보안메일을 열 수 있나요?", "content": "카드 답변 내용 152입니다." },
  { "subcategory": "체크카드", "title": "PC에서 암호화된 보안메일이 열리지 않아요.", "content": "카드 답변 내용 153입니다." },
  { "subcategory": "체크카드", "title": "카드 이용내역서 보안 프로그램 재설치 시 기존에 설치된 보안 프로그램 삭제는 어떻게 하나요?", "content": "카드 답변 내용 154입니다." },
  { "subcategory": "체크카드", "title": "체크카드 이용내역서를 신청했는데 이메일이 오지 않습니다.", "content": "카드 답변 내용 155입니다." },
  { "subcategory": "체크카드", "title": "체크카드 이용내역서를 받았는데 글씨가 깨져보입니다.", "content": "카드 답변 내용 156입니다." },
  { "subcategory": "체크카드", "title": "결제계좌에 타행수표로 입금된 금액이 있는데 체크카드 사용이 가능한가요", "content": "카드 답변 내용 157입니다." },
  { "subcategory": "체크카드", "title": "아파트관리비 자동이체(자동납부) 신청이 가능한가요?", "content": "카드 답변 내용 158입니다." },
  { "subcategory": "체크카드", "title": "해외이용시, 출금 수수료는 어떻게 되나요?", "content": "카드 답변 내용 159입니다." },
  { "subcategory": "체크카드", "title": "해외에서만 카드 사용이 안 되도록 정지하고 싶어요", "content": "카드 답변 내용 160입니다." },
  { "subcategory": "체크카드", "title": "해외에서 카드를 분실하였습니다. 어떻게 분실신고를 해야 하나요?", "content": "카드 답변 내용 161입니다." },
  { "subcategory": "체크카드", "title": "해외 이용한 거래를 취소하고 싶은데 방법은 어떻게 되나요?", "content": "카드 답변 내용 162입니다." },
  { "subcategory": "체크카드", "title": "해외에서 체크카드를 이용했는데 며칠후에 출금되었습니다.", "content": "카드 답변 내용 163입니다." },
  { "subcategory": "체크카드", "title": "카드가 정상인데 해외에서 사용이 되지 않습니다.", "content": "카드 답변 내용 164입니다." },
  { "subcategory": "체크카드", "title": "해외출국 예정입니다 출국 전에 조치해야 할 것은 무엇인가요?", "content": "카드 답변 내용 165입니다." },
  { "subcategory": "체크카드", "title": "체크카드로 해외에서 이용할 경우 수수료가 있나요?", "content": "카드 답변 내용 166입니다." },
  { "subcategory": "체크카드", "title": "국내전용카드를 소지하고 있는데 해외에서 이용하려면 어떻게 하나요", "content": "카드 답변 내용 167입니다." },
  { "subcategory": "체크카드", "title": "체크카드 사고신고(분실/도난) 등록했어요. 후불교통카드 사용이 바로 안되는건가요?", "content": "카드 답변 내용 168입니다." },
  { "subcategory": "체크카드", "title": "만18세 미만의 미성년자의 경우에도 후불교통기능을 이용할 수 있나요?", "content": "카드 답변 내용 169입니다." },
  { "subcategory": "체크카드", "title": "체크카드에 교통카드 기능이 있나요?", "content": "카드 답변 내용 170입니다." },
  { "subcategory": "체크카드", "title": "카드를 해지하려면 어떻게 해야하나요?", "content": "카드 답변 내용 171입니다." },
  { "subcategory": "체크카드", "title": "도난/분실 카드로 부정사용이 발생하였는데, 보상대상 기간은 어떻게 되나요?", "content": "카드 답변 내용 172입니다." },
  { "subcategory": "체크카드", "title": "분실카드로 부정사용이 발생했는데 어떻게 해야 하나요?", "content": "카드 답변 내용 173입니다." },
  { "subcategory": "체크카드", "title": "이용내역서를 받고 싶지 않은데 어떻게 해야 하나요?", "content": "카드 답변 내용 174입니다." },
  { "subcategory": "체크카드", "title": "체크카드 거래내역을 알고 싶어요 어떻게해야하나요?", "content": "카드 답변 내용 175입니다." },
  { "subcategory": "체크카드", "title": "체크카드 이용건을 취소 했는데 언제 환불 되나요?", "content": "카드 답변 내용 176입니다." },
  { "subcategory": "체크카드", "title": "카드승인 SMS를 신청하면 계좌 입출금내역도 같이 발송되나요?", "content": "카드 답변 내용 177입니다." },
  { "subcategory": "체크카드", "title": "카드 승인내역 조회는 어디서 할 수 있나요?", "content": "카드 답변 내용 178입니다." },
  { "subcategory": "체크카드", "title": "같은금액이 두번 승인되었을 경우 어떻게 하나요?", "content": "카드 답변 내용 179입니다." },
  { "subcategory": "체크카드", "title": "카드로 국세나 지방세 납부가 가능한가요?", "content": "카드 답변 내용 180입니다." },
  { "subcategory": "체크카드", "title": "체크카드 이용시간은 어떻게 되나요?", "content": "카드 답변 내용 181입니다." },
  { "subcategory": "체크카드", "title": "카드를 추가 발급 받았는데, 기존 카드와 통합한도 인가요?", "content": "카드 답변 내용 182입니다." },
  { "subcategory": "체크카드", "title": "카드결제계좌를 어디서 변경하나요?", "content": "카드 답변 내용 183입니다." },
  { "subcategory": "체크카드", "title": "ISP 비밀번호가 3회 오류되었는데 어떻게 해야하나요?", "content": "카드 답변 내용 184입니다." },
  { "subcategory": "체크카드", "title": "카드비밀번호 오류로 이용이 안 된다고 하는데 어떻게 해야하나요", "content": "카드 답변 내용 185입니다." },
  { "subcategory": "체크카드", "title": "카드비밀번호가 기억 안나는데 어떻게해야 하나요?", "content": "카드 답변 내용 186입니다." },
  { "subcategory": "체크카드", "title": "SMS 휴대폰번호 변경은 어떻게 하나요?", "content": "카드 답변 내용 187입니다." },
  { "subcategory": "체크카드", "title": "카드 발급 후 주소가 변경되었습니다. 변경된 주소로 카드를 받을 수 있나요?", "content": "카드 답변 내용 188입니다." },
  { "subcategory": "체크카드", "title": "분실과 훼손으로 인한 재발급 신청은 어떻게 하나요?", "content": "카드 답변 내용 189입니다." },
  { "subcategory": "체크카드", "title": "다른 사람이 대신 카드를 받을 수 있나요?", "content": "카드 답변 내용 190입니다." },
  { "subcategory": "체크카드", "title": "부재중으로 카드가 반송되었다고 하는데 다시 배송 받는 방법은 어떻게 되나요?", "content": "카드 답변 내용 191입니다." },
  { "subcategory": "체크카드", "title": "발급/배송상태 조회는 어떻게 할 수 있나요?", "content": "카드 답변 내용 192입니다." },
  { "subcategory": "프렌즈 체크카드", "title": "라이언 디자인 카드인데, Local(국내전용)로 신청하고 싶어요.", "content": "카드 답변 내용 193입니다." },
  { "subcategory": "체크카드", "title": "체크카드 발급대상은 어떻게 되나요?", "content": "카드 답변 내용 194입니다." },
  { "subcategory": "체크카드", "title": "체크카드를 해외에서 이용할 수 있나요?", "content": "카드 답변 내용 195입니다." },
  { "subcategory": "체크카드", "title": "인터넷/모바일 쇼핑을 통해 결제하려고 하는데 '카카오뱅크' 체크카드를 어떻게 선택할 수 있나요?", "content": "카드 답변 내용 196입니다." },
  { "subcategory": "체크카드", "title": "체크카드 이용한도 상향은 어떻게 하나요", "content": "카드 답변 내용 197입니다." },
  { "subcategory": "체크카드", "title": "체크카드 한도가 어떻게 되나요?", "content": "카드 답변 내용 198입니다." },
  { "subcategory": "체크카드", "title": "카드번호나 유효기한 그리고 CVC번호를 확인할 수 있나요?", "content": "카드 답변 내용 199입니다." },
  { "subcategory": "체크카드", "title": "한 계좌에 카드를 추가로 발급 가능한가요?", "content": "카드 답변 내용 200입니다." },
  { "subcategory": "프렌즈 체크카드", "title": "체크카드 이용내역을 보면, 해외결제건에 대한 캐시백이 0원으로 보여집니다.", "content": "카드 답변 내용 201입니다." }
]